art_fid/__init__.py
art_fid/__main__.py
art_fid/art_fid.py
art_fid/image_metrics.py
art_fid/inception.py
art_fid/utils.py
art_fid-0.0.2.dist-info/METADATA
art_fid-0.0.2.dist-info/WHEEL
art_fid-0.0.2.dist-info/entry_points.txt
art_fid-0.0.2.dist-info/top_level.txt
art_fid-0.0.2.dist-info/RECORD
