Metadata-Version: 2.1
Name: art-fid
Version: 0.0.2
Summary: ArtFID: Quantitative Evaluation of Neural Style Transfer
Home-page: https://github.com/matthias-wright/art-fid
Author: Matthias Wright
License: Apache License 2.0
Requires-Python: >=3.8
Requires-Dist: numpy <2,>=1.19.5
Requires-Dist: Pillow >=7.1.2
Requires-Dist: tqdm >=4.60.0
Requires-Dist: scikit-learn
Requires-Dist: torch
Requires-Dist: lpips
Requires-Dist: torchvision >=0.9.0
Requires-Dist: scipy
Requires-Dist: requests <3,>=2.27.0
